interpax_fft/__init__.py
interpax_fft/_fft.py
interpax_fft/_interp_utils.py
interpax_fft/_mmt.py
interpax_fft/_series.py
interpax_fft/_utils.py
interpax_fft/_version.py
interpax_fft/py.typed
interpax_fft-0.0.3.dist-info/licenses/LICENSE
interpax_fft-0.0.3.dist-info/METADATA
interpax_fft-0.0.3.dist-info/WHEEL
interpax_fft-0.0.3.dist-info/top_level.txt
interpax_fft-0.0.3.dist-info/RECORD
