Metadata-Version: 2.4
Name: interpax_fft
Version: 0.0.3
Summary: Fourier interpolation and function approximation with JAX
Home-page: https://github.com/unalmis/interpax_fft
Author: Kaya Unalmis
Author-email: kunalmis@stanford.edu
License: MIT
Project-URL: Issues Tracker, https://github.com/unalmis/interpax_fft/issues
Project-URL: Contributing, https://github.com/unalmis/interpax_fft/blob/master/CONTRIBUTING.rst
Project-URL: Source Code, https://github.com/unalmis/interpax_fft/
Project-URL: Documentation, https://unalmis.github.io/interpax_fft/
Keywords: interpolation fourier approximation
Classifier: Development Status :: 3 - Alpha
Classifier: Intended Audience :: Science/Research
Classifier: License :: OSI Approved :: MIT License
Classifier: Natural Language :: English
Classifier: Programming Language :: Python :: 3
Classifier: Programming Language :: Python :: 3.10
Classifier: Programming Language :: Python :: 3.11
Classifier: Programming Language :: Python :: 3.12
Classifier: Programming Language :: Python :: 3.13
Classifier: Topic :: Scientific/Engineering
Classifier: Topic :: Scientific/Engineering :: Mathematics
Classifier: Typing :: Typed
Requires-Python: >=3.10
License-File: LICENSE
Requires-Dist: equinox<0.14,>=0.11.0
Requires-Dist: jax!=0.5.1,!=0.5.2,!=0.6.0,!=0.7.1,<=0.8.1,>=0.5.0
Requires-Dist: jaxtyping<0.4.0,>=0.2.24
Requires-Dist: numpy<2.4,>=1.20.0
Dynamic: author
Dynamic: author-email
Dynamic: classifier
Dynamic: description
Dynamic: description-content-type
Dynamic: home-page
Dynamic: keywords
Dynamic: license
Dynamic: license-file
Dynamic: project-url
Dynamic: requires-dist
Dynamic: requires-python
Dynamic: summary
